vedro_pyppeteer/__init__.py
vedro_pyppeteer/_browser_context.py
vedro_pyppeteer/_screenshot_path.py
vedro_pyppeteer/_vedro_pyppeteer.py
vedro_pyppeteer/py.typed
vedro_pyppeteer-1.1.0.dist-info/LICENSE
vedro_pyppeteer-1.1.0.dist-info/METADATA
vedro_pyppeteer-1.1.0.dist-info/WHEEL
vedro_pyppeteer-1.1.0.dist-info/top_level.txt
vedro_pyppeteer-1.1.0.dist-info/RECORD
