Metadata-Version: 2.1
Name: vedro-pyppeteer
Version: 1.1.0
Summary: Vedro + pyppeteer
Home-page: https://github.com/nikitanovosibirsk/vedro-pyppeteer
Author: Nikita Tsvetkov
Author-email: nikitanovosibirsk@yandex.com
License: Apache-2.0
Classifier: License :: OSI Approved :: Apache Software License
Classifier: Programming Language :: Python :: 3.8
Classifier: Programming Language :: Python :: 3.9
Classifier: Programming Language :: Python :: 3.10
Classifier: Typing :: Typed
Requires-Python: >=3.8
License-File: LICENSE
Requires-Dist: vedro (<2.0,>=1.7)
Requires-Dist: pyppeteer (<1.1,>=0.2.6)
